Sudip_snp/__init__.py
Sudip_snp-0.1.dist-info/METADATA
Sudip_snp-0.1.dist-info/WHEEL
Sudip_snp-0.1.dist-info/top_level.txt
Sudip_snp-0.1.dist-info/RECORD
