Metadata-Version: 2.1
Name: Sudip-snp
Version: 0.1
Summary: Using this module and supplying the location of your genelocus txt files we can download snp files
Home-page: UNKNOWN
Author: Sudipan Paul
Author-email: sudipanpaul6@gmail.com
License: UNKNOWN
Platform: UNKNOWN
Requires-Dist: webdriver-manager
Requires-Dist: selenium
Requires-Dist: pandas
